AUTHORS
LICENSE
MANIFEST.in
README.md
requirements.txt
requirements_docs.txt
setup.py
doc/Makefile
doc/Makefile.cmds
doc/api.rst
doc/changelog.rst
doc/cli-advanced.rst
doc/cli.rst
doc/conf.py
doc/description.rst
doc/devel.rst
doc/index.rst
doc/make.bat
doc/quickstart.rst
doc/repeat.sh
doc/stack_imgs.py
resources/code/similarity.py
resources/code/translation.py
resources/examples/sample1.png
resources/examples/sample2.png
resources/examples/sample3.png
resources/examples/sample3c.jpg
resources/examples/sample4.png
resources/examples/constraints/three.png
resources/examples/constraints/tricky.png
resources/examples/constraints/two.png
src/imreg_dft/__init__.py
src/imreg_dft/cli.py
src/imreg_dft/imreg.py
src/imreg_dft/loader.py
src/imreg_dft/reporting.py
src/imreg_dft/show.py
src/imreg_dft/tform.py
src/imreg_dft/tiles.py
src/imreg_dft/utils.py
src/imreg_dft_nw.egg-info/PKG-INFO
src/imreg_dft_nw.egg-info/SOURCES.txt
src/imreg_dft_nw.egg-info/dependency_links.txt
src/imreg_dft_nw.egg-info/entry_points.txt
src/imreg_dft_nw.egg-info/requires.txt
src/imreg_dft_nw.egg-info/top_level.txt
src/imreg_dft_nw.egg-info/zip-safe
tests/Makefile
tests/regressiontests/Makefile
tests/regressiontests/check_similarity.sh
tests/regressiontests/img2mat.py
tests/unittests/__init__.py
tests/unittests/imreg.py
tests/unittests/utils.py