Metadata-Version: 2.1
Name: imreg-dft-nw
Version: 2.0.0
Summary: Tiny no-warn fork of imreg_dft, Image registration utility using algorithms based on discrete Fourier transform (DFT, FFT), To get rid of those np.bool deprecation warnings.
Home-page: https://github.com/xtofl/imreg_dft_nw
Author: Matěj Týč
Author-email: matej.tyc@gmail.com
License: BSD
Classifier: Development Status :: 4 - Beta
Classifier: Natural Language :: English
Classifier: Programming Language :: Python :: 3
Classifier: Intended Audience :: Science/Research
Classifier: Intended Audience :: Education
Classifier: Topic :: Utilities
Classifier: Topic :: Scientific/Engineering :: Image Recognition
Classifier: Operating System :: OS Independent
Classifier: License :: OSI Approved :: BSD License
Provides-Extra: plotting
Provides-Extra: loading images
Provides-Extra: better performance
License-File: LICENSE
License-File: AUTHORS
